[
  {
    "id": "dl-the-golden-horseshoe",
    "name": "The Golden Horseshoe",
    "park": "Disneyland Park",
    "url": "https://disneyland.disney.go.com/dining/disneyland/golden-horseshoe-restaurant/menus/lunch-and-dinner/",
    "added": [],
    "removed": [
      "Lunch And Dinner Menu"
    ]
  },
  {
    "id": "dl-the-tropical-hideaway",
    "name": "The Tropical Hideaway",
    "park": "Disneyland Park",
    "url": "https://disneyland.disney.go.com/dining/disneyland/tropical-hideaway/menus/snack/",
    "added": [],
    "removed": [
      "— Snack Menu"
    ]
  },
  {
    "id": "dl-tianas-palace",
    "name": "Tiana's Palace",
    "park": "Disneyland Park",
    "url": "https://disneyland.disney.go.com/dining/disneyland/tianas-palace/menus/lunch-and-dinner/",
    "added": [],
    "removed": [
      "Lunch And Dinner Menu"
    ]
  },
  {
    "id": "dl-tiki-juice-bar",
    "name": "Tiki Juice Bar",
    "park": "Disneyland Park",
    "url": "https://disneyland.disney.go.com/dining/disneyland/tiki-juice-bar/menus/snack/",
    "added": [],
    "removed": [
      "— Snack Menu"
    ]
  },
  {
    "id": "dl-troubadour-tavern",
    "name": "Troubadour Tavern",
    "park": "Disneyland Park",
    "url": "https://disneyland.disney.go.com/dining/disneyland/troubadour-tavern/menus/",
    "added": [],
    "removed": [
      "— Snack Menu",
      "— Skyway Straw Clip"
    ]
  },
  {
    "id": "epcot-akershus-royal-banquet-hall-breakfast",
    "name": "Akershus Royal Banquet Hall (Breakfast)",
    "park": "EPCOT",
    "url": "https://disneyworld.disney.go.com/dining/epcot/akershus-royal-banquet-hall/menus/breakfast/",
    "added": [],
    "removed": [
      "Breakfast Menu"
    ]
  },
  {
    "id": "epcot-akershus-royal-banquet-hall-lunch",
    "name": "Akershus Royal Banquet Hall (Lunch)",
    "park": "EPCOT",
    "url": "https://disneyworld.disney.go.com/dining/epcot/akershus-royal-banquet-hall/menus/lunch/",
    "added": [],
    "removed": [
      "Lunch Menu"
    ]
  },
  {
    "id": "epcot-akershus-royal-banquet-hall-dinner",
    "name": "Akershus Royal Banquet Hall (Dinner)",
    "park": "EPCOT",
    "url": "https://disneyworld.disney.go.com/dining/epcot/akershus-royal-banquet-hall/menus/dinner/",
    "added": [],
    "removed": [
      "Dinner Menu"
    ]
  },
  {
    "id": "epcot-biergarten-restaurant-lunch",
    "name": "Biergarten Restaurant (Lunch)",
    "park": "EPCOT",
    "url": "https://disneyworld.disney.go.com/dining/epcot/biergarten-restaurant/menus/lunch/",
    "added": [],
    "removed": [
      "Lunch Menu"
    ]
  },
  {
    "id": "epcot-biergarten-restaurant-dinner",
    "name": "Biergarten Restaurant (Dinner)",
    "park": "EPCOT",
    "url": "https://disneyworld.disney.go.com/dining/epcot/biergarten-restaurant/menus/dinner/",
    "added": [],
    "removed": [
      "Dinner Menu"
    ]
  },
  {
    "id": "epcot-block-and-hans",
    "name": "Block & Hans",
    "park": "EPCOT",
    "url": "https://disneyworld.disney.go.com/dining/epcot/block-hans/menus/bar-%E2%80%93-lounge/",
    "added": [],
    "removed": [
      "— Bar – Lounge Menu",
      "— Cinnamon-glazed Nuts"
    ]
  },
  {
    "id": "epcot-canada-popcorn-cart",
    "name": "Canada Popcorn Cart",
    "park": "EPCOT",
    "url": "https://disneyworld.disney.go.com/dining/epcot/popcorn-at-canada-pavilion/menus/snack/",
    "added": [],
    "removed": [
      "— Snack Menu"
    ]
  },
  {
    "id": "epcot-chefs-de-france-lunch",
    "name": "Chefs de France (Lunch)",
    "park": "EPCOT",
    "url": "https://disneyworld.disney.go.com/dining/epcot/chefs-de-france/menus/lunch/",
    "added": [],
    "removed": [
      "Lunch Menu"
    ]
  },
  {
    "id": "epcot-chefs-de-france-dinner",
    "name": "Chefs de France (Dinner)",
    "park": "EPCOT",
    "url": "https://disneyworld.disney.go.com/dining/epcot/chefs-de-france/menus/dinner/",
    "added": [],
    "removed": [
      "Dinner Menu"
    ]
  },
  {
    "id": "epcot-choza-de-margarita",
    "name": "Choza de Margarita",
    "park": "EPCOT",
    "url": "https://disneyworld.disney.go.com/dining/epcot/choza-de-margarita/menus/snack/",
    "added": [],
    "removed": [
      "— Snack Menu"
    ]
  },
  {
    "id": "epcot-connections-cafe",
    "name": "Connections Café (Starbucks)",
    "park": "EPCOT",
    "url": "https://disneyworld.disney.go.com/dining/epcot/connections-cafe/menus/coffee-%E2%80%93-bakery/",
    "added": [
      "Blue Coconut Lemonade Energy Refresher - Grande"
    ],
    "removed": [
      "— Coffee – Bakery Menu"
    ]
  },
  {
    "id": "epcot-connections-eatery",
    "name": "Connections Eatery",
    "park": "EPCOT",
    "url": "https://disneyworld.disney.go.com/dining/epcot/connections-eatery/menus/",
    "added": [
      "— House-made Pepperoni Pizza",
      "— House-made Cheese Pizza",
      "— French Fries",
      "— Peach Whiskey Iced Tea"
    ],
    "removed": [
      "Lunch And Dinner Menu",
      "— Pepperoni Pizza",
      "— French Fries with Sea Salt",
      "— Rainstorm Pinot Noir Rosé, Oregon",
      "— Broadside Cabernet Sauvignon, California"
    ]
  },
  {
    "id": "epcot-coral-reef-restaurant",
    "name": "Coral Reef Restaurant",
    "park": "EPCOT",
    "url": "https://disneyworld.disney.go.com/dining/epcot/coral-reef-restaurant/menus/dinner/",
    "added": [],
    "removed": [
      "Dinner Menu"
    ]
  },
  {
    "id": "epcot-crepes-a-emporter",
    "name": "Crêpes À Emporter by La Crêperie de Paris",
    "park": "EPCOT",
    "url": "https://disneyworld.disney.go.com/dining/epcot/crepes-a-emporter/menus/",
    "added": [],
    "removed": [
      "Lunch And Dinner Menu"
    ]
  },
  {
    "id": "epcot-fife-and-drum-tavern",
    "name": "Fife & Drum Tavern",
    "park": "EPCOT",
    "url": "https://disneyworld.disney.go.com/dining/epcot/fife-and-drum-tavern/menus/snack/",
    "added": [],
    "removed": [
      "— Snack Menu"
    ]
  },
  {
    "id": "epcot-funnel-cake",
    "name": "Funnel Cake – EPCOT",
    "park": "EPCOT",
    "url": "https://disneyworld.disney.go.com/dining/epcot/funnel-cake/menus/",
    "added": [],
    "removed": [
      "— Snack Menu"
    ]
  },
  {
    "id": "epcot-garden-grill-restaurant-breakfast",
    "name": "Garden Grill Restaurant (Breakfast)",
    "park": "EPCOT",
    "url": "https://disneyworld.disney.go.com/dining/epcot/garden-grill-restaurant/menus/breakfast/",
    "added": [],
    "removed": [
      "Breakfast Menu"
    ]
  },
  {
    "id": "epcot-garden-grill-restaurant-lunch",
    "name": "Garden Grill Restaurant (Lunch)",
    "park": "EPCOT",
    "url": "https://disneyworld.disney.go.com/dining/epcot/garden-grill-restaurant/menus/lunch/",
    "added": [],
    "removed": [
      "Lunch Menu"
    ]
  },
  {
    "id": "epcot-garden-grill-restaurant-dinner",
    "name": "Garden Grill Restaurant (Dinner)",
    "park": "EPCOT",
    "url": "https://disneyworld.disney.go.com/dining/epcot/garden-grill-restaurant/menus/dinner/",
    "added": [],
    "removed": [
      "Dinner Menu"
    ]
  },
  {
    "id": "epcot-gelateria-toscana",
    "name": "Gelateria Toscana",
    "park": "EPCOT",
    "url": "https://disneyworld.disney.go.com/dining/epcot/gelateria-toscana/menus/snack/",
    "added": [],
    "removed": [
      "— Snack Menu"
    ]
  }
]