{
  "sections": [
    {
      "title": "menu",
      "items": [
        "Via Napoli Ristorante e Pizzeria"
      ]
    },
    {
      "title": "Lunch Menu",
      "items": []
    },
    {
      "title": "Lunch Menu",
      "items": [
        "— Tris di Bruschetta",
        "— Calamari Fritti",
        "— Mozzarella Caprese",
        "— Arancini",
        "— Homemade Focaccia",
        "— Tagliere (serves 2)",
        "— Cesare*",
        "— House Salad",
        "— Tortellini",
        "— Spaghetti e Polpettine",
        "— Penne Alla Bolognese",
        "— Manicotti",
        "— Fettucine via Napoli",
        "— Branzino*",
        "— Chicken Parmesan",
        "— Filetto di Manzo*",
        "— Green Beans",
        "— Fingerling Potatoes",
        "— Carciofi Pizza - Individual",
        "— Carciofi Pizza - Large",
        "— Carciofi Pizza - Half Meter",
        "— Prosciutto e Melone Pizza - Individual",
        "— Prosciutto e Melone Pizza - Large",
        "— Prosciutto e Melone Pizza - Half Meter",
        "— Capricciosa Pizza - Individual",
        "— Capricciosa Pizza - Large",
        "— Capricciosa Pizza - Half Meter",
        "— Quattro Formaggi Pizza - Individual",
        "— Quattro Formaggi Pizza - Large",
        "— Quattro Formaggi Pizza - Half Meter",
        "— Margherita Pizza - Individual",
        "— Margherita Pizza - Large",
        "— Margherita Pizza - Half Meter",
        "— Meat Lover Pizza - Individual",
        "— Meat Lover Pizza - Large",
        "— Meat Lover Pizza - Half Meter",
        "— Build Your Own Pizza (22 | 36 | 48)",
        "— Classic Toppings (4.5 | 6 | 7 each)",
        "— Specialty Toppings (5 | 7 | 8.5 each)",
        "— Prosciutto (7 | 9 | 11 each)",
        "— Tiramisù",
        "— Cannolo Siciliano",
        "— Cannolo di Cioccolato e Nocciola",
        "— Cheesecake alle Fragole",
        "— Torta al Cioccolato",
        "— Gelati e Sorbetti",
        "— Limoncello Float",
        "— Bocconcini",
        "— Pizza Margarita",
        "— Spaghetti",
        "— Chicken Tender",
        "— Bombolone",
        "— Italian Soda",
        "— Italian Water",
        "— Strawberry Acqua Fresca",
        "— Dolce Vita",
        "— Frozen Vulcano",
        "— Virgin Pina Colada",
        "— Sicily 75",
        "— Amalfi Refresher",
        "— Espresso",
        "— Double Espresso",
        "— Cappuccino",
        "— Limoncello Mule",
        "— Americano",
        "— Sicilian Sunset",
        "— Via Vesuvio",
        "— Negroni",
        "— Amaretto Sour",
        "— Torcello Old Fashioned",
        "— Via Napoli's Earth Cocktail",
        "— Italian Siesta",
        "— Bellini",
        "— Lemon Drop",
        "— Strawberry Limoncello",
        "— Aperol Spritz",
        "— Tiramisù Martini",
        "— Espresso Martini",
        "— Cannoli Martini",
        "— Prosecco Terre di Bacco",
        "— Gavi Batasiolo",
        "— Langhe Terre di Bacco",
        "— Italian Beer Sangria",
        "— Full Wine List Available",
        "— Peroni",
        "— Bud Light",
        "— Blue Moon",
        "— Seasonal Draft",
        "— Menabrea Bionda",
        "— Menabrea Ambrata",
        "— White Wine Flight",
        "— Via Napoli Flight",
        "— Red Flight",
        "— Sangria Flight",
        "— Beer Flight (4.5 oz pours)",
        "* Consuming raw or undercooked meats, poultry, seafood, shellfish, or eggs may increase your risk of foodborne illness.",
        "Our plant-based menu items are made without animal meat, dairy, eggs and honey.",
        "Notice of Right to Opt Out of Sale/Sharing",
        "— Manage Consent Preferences",
        "— Selling, Sharing, Targeted Advertising",
        "checkbox label label"
      ]
    }
  ]
}