{
  "sections": [
    {
      "title": "menu",
      "items": [
        "50's Prime Time Café"
      ]
    },
    {
      "title": "Dinner Menu",
      "items": []
    },
    {
      "title": "Dinner Menu",
      "items": [
        "— Cornbread Skillet",
        "— Shrimp Cocktail",
        "— Beer-battered Onion Rings",
        "— Mixed Salad",
        "— Cousin Bob’s Chowder",
        "— Aunt Liz's Golden Fried Chicken",
        "— A Sampling of Mom's Favorite Recipes",
        "— Caesar Salad with Chicken",
        "— Cousin Harold's Rigatoni Pasta",
        "— Grilled Salmon*",
        "— Grandpa Jean’s Chicken Pot Pie",
        "— Mom's Old-fashioned Pot Roast",
        "— Cousin Megan's Traditional Meatloaf",
        "— 50’s Prime Time Café Blue Plate Special",
        "Dad's Favorite Chocolate-Peanut Butter Layered Cake",
        "Dad's Favorite Chocolate-Peanut Butter Layered Cake À la Mode",
        "— Raspberry Key Lime Pie",
        "— Traditional Warm Apple Crisp",
        "— Traditional Warm Apple Crisp À la Mode",
        "— Vanilla Strawberry Shortcake",
        "— Garden Salad",
        "— Vegetable Platter",
        "— Corn Chowder",
        "— Goofy's Salmon",
        "— Sloppy Joe Sandwich",
        "— Grandpa's Grilled Chicken",
        "— Aunt Betty's Chicken Strips",
        "— Green Beans & Carrots",
        "— Stained Glass Dessert",
        "— Grandma's Macaroni & Cheese",
        "— Corn",
        "— Mashed Potatoes",
        "— Fruit Salad",
        "— Seasonal Cupcake",
        "— Specialty Character Drink",
        "— Mickey's Bee Bop Drink",
        "— Flavored Sodas",
        "— Hand-scooped Floats",
        "— Freshly Brewed Joffrey's Coffee™",
        "— Peanut Butter & Jelly Milk Shake",
        "— Handmade Milk Shakes",
        "— Enchanting Ember Lemonade",
        "— Enchanted Grove Lime Splash",
        "— Grandma's Picnic Punch",
        "— The Tune-In PBJ Cocktail",
        "— Island Fusion Punch",
        "— Toasted Marshmallow Old Fashioned",
        "— Patrón Platinum Margarita",
        "— Dad's Electric Lemonade",
        "— Espresso Martini",
        "— Coconut Gimlet",
        "— Ultimate Long Island Iced Tea",
        "Marsuret Prosecco, Valdobbiadene Superiore NV",
        "— Coppo Mocscato d'Asti Moncalvina",
        "King Estate Pinot Gris, Willamette Valley",
        "Kim Crawford Sauvignon Blanc, Marlborough",
        "Fess Parker Chardonnay, Santa Barbara County",
        "MacMurray Estate Vineyards Pinot Noir, Central Coast",
        "— Decoy by Duckhorn Merlot, Sonoma County",
        "Louis M. Martini Cabernet Sauvignon, Sonoma County",
        "— Bud Light Lager",
        "— Miller Lite",
        "Yuengling Traditional Draft – Pottsville, PA",
        "— Samuel Adams Seasonal Draft",
        "— Cigar City Ja Alai IPA Draft",
        "— Stella Artois",
        "— Corona Extra",
        "— Blue Moon Belgian White",
        "— Schöfferhofer Grapefruit Hefeweizen",
        "— New Belgium Fat Tire",
        "— Angry Orchard Crisp Apple Hard Cider",
        "— Michelob Ultra Draft - St. Louis, MO",
        "White Claw Black Cherry Hard Seltzer - Chicago, IL",
        "— Cousin Bob's Chowder",
        "— Mom’s Old-fashioned Pot Roast",
        "— Caesar Salad",
        "— Mom's Favorite Recipes",
        "* Consuming raw or undercooked meats, poultry, seafood, shellfish, or eggs may increase your risk of foodborne illness.",
        "Our plant-based menu items are made without animal meat, dairy, eggs and honey.",
        "Notice of Right to Opt Out of Sale/Sharing",
        "— Manage Consent Preferences",
        "— Selling, Sharing, Targeted Advertising",
        "checkbox label label"
      ]
    }
  ]
}